server/.gitignore
server/__init__.py
server/agents/__init__.py
server/agents/base.py
server/agents/config/example_agent.yaml
server/agents/example_agent.py
server/agents/kairos/__init__.py
server/agents/kairos/chat_agent.py
server/agents/memory_agent.py
server/agents/utils.py
server/app_config.py
server/auth.py
server/config.py
server/database.py
server/lib/__init__.py
server/lib/openai.py
server/lib/qdrant.py
server/main.py
server/memory_graph.py
server/models.py
server/routes/__init__.py
server/routes/chat.py
server/routes/epics.py
server/routes/goals.py
server/routes/kairos.py
server/routes/memory.py
server/routes/openai_proxy.py
server/routes/phases.py
server/routes/planner.py
server/routes/profile.py
server/routes/tasks.py
server/routes/terminal.py
server/routes/test_runner.py
server/routes/vision.py
server/routes/webhooks.py
server/schemas/__init__.py
server/schemas/memory_entry.py
server/schemas/prompt_feedback.py
server/schemas/task_plan.py
server/scripts/migrate_to_qdrant.py
server/scripts/seed_qdrant.py
server/services/__init__.py
server/services/agent_actions.py
server/services/chat_store.py
server/services/profile_service.py
server/services/prompt_modifier.py
server/services/qdrant_service.py
server/services/runtime_logs.py
server/services/vision_service.py
server/services/youtube_oauth.py
server/static/assets/index-Bqb88LVT.css
server/static/assets/index-vtnI5AxH.js
server/static/assets/index-vtnI5AxH.js.map
server/static/icon-192x192.png
server/static/icon-512x512.png
server/static/index.html
server/static/manifest.webmanifest
server/static/registerSW.js
server/static/sw.js
server/static/sw.js.map
server/static/vite.svg
server/static/workbox-4245c4a1.js
server/static/workbox-4245c4a1.js.map
server/utils/db_utils.py
server/utils/rules_engine.py
server/utils/stats_utils.py
server/utils/task_validation.py
buildmode_ai-0.1.0.dist-info/LICENSE
buildmode_ai-0.1.0.dist-info/METADATA
buildmode_ai-0.1.0.dist-info/WHEEL
buildmode_ai-0.1.0.dist-info/RECORD
