Metadata-Version: 2.3
Name: buildmode-ai
Version: 0.1.0
Summary: BuildMode.AI backend service
Author: BuildMode Team
Author-email: team@buildmode.ai
Requires-Python: >=3.11,<3.13
Classifier: Programming Language :: Python :: 3
Classifier: Programming Language :: Python :: 3.11
Classifier: Programming Language :: Python :: 3.12
Requires-Dist: APScheduler (==3.10.4)
Requires-Dist: PyYAML (==6.0.1)
Requires-Dist: SQLAlchemy (==2.0.30)
Requires-Dist: fastapi (==0.104.1)
Requires-Dist: httpx (==0.27.0)
Requires-Dist: itsdangerous (==2.1.2)
Requires-Dist: networkx (==3.3)
Requires-Dist: numpy (>=2.3.2,<3.0.0)
Requires-Dist: openai (>=1.13.3,<2.0.0)
Requires-Dist: psycopg[binary] (>=3.2,<4.0)
Requires-Dist: pydantic (==2.5.0)
Requires-Dist: pydantic-settings (==2.1.0)
Requires-Dist: python-dotenv (==1.1.1)
Requires-Dist: qdrant-client (==1.15.1)
Requires-Dist: requests (==2.32.4)
Requires-Dist: slowapi (>=0.1.9,<0.2.0)
Requires-Dist: uvicorn (==0.29.0)
